pywindow/__init__.py
pywindow/io_tools.py
pywindow/molecular.py
pywindow/tables.py
pywindow/trajectory.py
pywindow/utilities.py
pywindowx2-2025.4.30.3.dist-info/licenses/LICENSE
pywindowx2-2025.4.30.3.dist-info/METADATA
pywindowx2-2025.4.30.3.dist-info/WHEEL
pywindowx2-2025.4.30.3.dist-info/top_level.txt
pywindowx2-2025.4.30.3.dist-info/RECORD
